setup.py
PyMeas.egg-info/PKG-INFO
PyMeas.egg-info/SOURCES.txt
PyMeas.egg-info/dependency_links.txt
PyMeas.egg-info/requires.txt
PyMeas.egg-info/top_level.txt
pymeas/image_processor.py